{
    "MNSA": {
        "LEFT": {
            "NECK_AXIS": {
                "type": "midpoint",
                "P1": null,
                "P2": null,
                "M1": null
            }
        },
        "RIGHT": {
            "NECK_AXIS": {
                "type": "midpoint",
                "P1": null,
                "P2": null,
                "M1": null
            }
        }
    },
    "ALDFA": {
        "LEFT": {
            "FEM_JOINT_LINE": {
                "type": "line",
                "P1": null,
                "P2": null
            }
        },
        "RIGHT": {
            "FEM_JOINT_LINE": {
                "type": "line",
                "P1": null,
                "P2": null
            }
        }
    },
    "TAMD": {
        "LEFT": {
            "TIB_JOINT_LINE": {
                "type": "line",
                "P1": null,
                "P2": null
            }
        },
        "RIGHT": {
            "TIB_JOINT_LINE": {
                "type": "line",
                "P1": null,
                "P2": null
            }
        }
    },
    "MAIN": {
        "LEFT": {
            "HIP": {
                "type": "point",
                "P1": [
                    493,
                    977
                ]
            },
            "KNEE": {
                "type": "point",
                "P1": [
                    430,
                    2319
                ]
            },
            "ANKLE": {
                "type": "midpoint",
                "P1": [
                    460,
                    3417
                ],
                "P2": [
                    540,
                    3411
                ],
                "M1": [
                    500.0,
                    3414.0
                ]
            },
            "AXIS_FEM": {
                "type": "axis",
                "TOP": {
                    "type": "midpoint",
                    "P1": [
                        442,
                        1239
                    ],
                    "P2": [
                        335,
                        1242
                    ],
                    "M1": [
                        388.5,
                        1240.5
                    ]
                },
                "BOT": {
                    "type": "midpoint",
                    "P1": [
                        481,
                        1989
                    ],
                    "P2": [
                        389,
                        1991
                    ],
                    "M1": [
                        435.0,
                        1990.0
                    ]
                }
            },
            "AXIS_TIB": {
                "type": "axis",
                "TOP": {
                    "type": "midpoint",
                    "P1": [
                        468,
                        2565
                    ],
                    "P2": [
                        385,
                        2579
                    ],
                    "M1": [
                        426.5,
                        2572.0
                    ]
                },
                "BOT": {
                    "type": "midpoint",
                    "P1": [
                        507,
                        3067
                    ],
                    "P2": [
                        444,
                        3074
                    ],
                    "M1": [
                        475.5,
                        3070.5
                    ]
                }
            }
        },
        "RIGHT": {
            "HIP": {
                "type": "point",
                "P1": [
                    1011,
                    1008
                ]
            },
            "KNEE": {
                "type": "point",
                "P1": [
                    1151,
                    2344
                ]
            },
            "ANKLE": {
                "type": "midpoint",
                "P1": [
                    1049,
                    3418
                ],
                "P2": [
                    1144,
                    3426
                ],
                "M1": [
                    1096.5,
                    3422.0
                ]
            },
            "AXIS_FEM": {
                "type": "axis",
                "TOP": {
                    "type": "midpoint",
                    "P1": [
                        1099,
                        1231
                    ],
                    "P2": [
                        1210,
                        1237
                    ],
                    "M1": [
                        1154.5,
                        1234.0
                    ]
                },
                "BOT": {
                    "type": "midpoint",
                    "P1": [
                        1098,
                        1616
                    ],
                    "P2": [
                        1185,
                        1615
                    ],
                    "M1": [
                        1141.5,
                        1615.5
                    ]
                }
            },
            "AXIS_TIB": {
                "type": "axis",
                "TOP": {
                    "type": "midpoint",
                    "P1": [
                        1115,
                        2568
                    ],
                    "P2": [
                        1206,
                        2572
                    ],
                    "M1": [
                        1160.5,
                        2570.0
                    ]
                },
                "BOT": {
                    "type": "midpoint",
                    "P1": [
                        1076,
                        3164
                    ],
                    "P2": [
                        1146,
                        3167
                    ],
                    "M1": [
                        1111.0,
                        3165.5
                    ]
                }
            }
        }
    }
}